management_command_decorator/__init__.py
management_command_decorator/apps.py
management_command_decorator/commands.py
management_command_decorator/decorator.py
management_command_decorator/migrations/__init__.py
django_management_command_decorator-0.0.7.dist-info/METADATA
django_management_command_decorator-0.0.7.dist-info/WHEEL
django_management_command_decorator-0.0.7.dist-info/licenses/LICENSE
django_management_command_decorator-0.0.7.dist-info/RECORD
