Metadata-Version: 2.3
Name: django_management_command_decorator
Version: 0.0.7
Summary: The django management decorator package
Project-URL: Homepage, https://github.com/srccast/django_management_command_decorator
Project-URL: Issues, https://github.com/srccast/django_management_command_decorator/issues
Author-email: Fabian Lange <fabian.lange@srccast.de>
License-File: LICENSE
Classifier: License :: OSI Approved :: MIT License
Classifier: Operating System :: OS Independent
Classifier: Programming Language :: Python :: 3
Requires-Python: >=3.8
Requires-Dist: django
Requires-Dist: wrapt
